SchedulePy/__init__.py
SchedulePy/module.py
SchedulePy-0.0.1.dist-info/LICENSE
SchedulePy-0.0.1.dist-info/METADATA
SchedulePy-0.0.1.dist-info/WHEEL
SchedulePy-0.0.1.dist-info/top_level.txt
SchedulePy-0.0.1.dist-info/RECORD
