Metadata-Version: 2.1
Name: SchedulePy
Version: 0.0.1
Summary: A job scheduling library that supports various time intervals
Home-page: https://github.com/DataShelf-Solutions/SchedulePy
Author: Anri Tvalabeishvili, Kristine Dzneladze, Ruso Kvesitadze
Author-email: anri.tvalabeishvili@gmail.com
Project-URL: Documentation, https://timeline-manager.readthedocs.io/en/latest/index.html
Project-URL: HomePage, https://github.com/DataShelf-Solutions/SchedulePy
Project-URL: Tracker, https://github.com/DataShelf-Solutions/SchedulePy/issues
Classifier: Programming Language :: Python :: 3
Classifier: License :: OSI Approved :: MIT License
Classifier: Operating System :: OS Independent
Requires-Python: >=3.6
License-File: LICENSE
